{
    "usings":["System"],
    "type":["BASE"],
    "inputtedParameter":[],
    "subBlockWhiteFilter":["&GROUP_DICE_ACTIONS"],
    "kr":[
        "합 패배시 트리거 기반 블록",
        "합 패배시 액션를 발생시키기 위한 기반 블록입니다",
        ""
    ],
    "en":[
        "Losing parrying Base Block",
        "Base block for invoking action when losing parrying",
        ""
    ],
    "jp":[
        "Losing parrying Base Block",
        "Base block for invoking action when losing parrying",
        ""
    ],
    "cn":[
        "Losing parrying Base Block",
        "Base block for invoking action when losing parrying",
        ""
    ]
}