{
    "usings":[],
    "type":["IF"],
    "inputtedParameter":[""],
    "subBlockWhiteFilter":["&ALL"],
    "kr":[
        "커스텀 조건 블록",
        "커스텀 조건 블록입니다. 텍스트창에서 오른쪽 마우스를 눌러서 무엇이든 직접 삽입시킬 수 있습니다",
        "코드 편집"
    ],
    "en":[
        "Custom IF block",
        "This is a custom if block. With the right mouse button in a text editor, You can insert any code you want",
        "Edit code"
    ],
    "jp":[
        "Custom IF block",
        "This is a custom if block. With the right mouse button in a text editor, You can insert any code you want",
        "Edit code"
    ],
    "cn":[
        "Custom IF block",
        "This is a custom if block. With the right mouse button in a text editor, You can insert any code you want",
        "Edit code"
    ]
}